{
  "id": "aedis-suggestions:81ecf2d7-e5de-4b7f-b7e3-c37e1bdbfc87",
  "space": "aedis/project/mnt-ai-tmp-aedis-gauntlet-egjaae",
  "kind": "aedis-suggestions",
  "title": "Follow-up suggestions for 81ecf2d7-e5de-4b7f-b7e3-c37e1bdbfc87",
  "summary": "Re-run the task with tighter scope around the failing files before attempting broader changes. Address the merge blocker first: \"core/main.ts\" modified without original content or diff — cannot rollback",
  "tags": [
    "suggestions",
    "verdict:failed"
  ],
  "createdAt": "2026-04-25T12:38:40.865Z",
  "updatedAt": "2026-04-25T12:38:40.867Z",
  "sourceSystem": "aedis",
  "repoId": "/mnt/ai/tmp/aedis-gauntlet-EGJAAE",
  "filePaths": [
    "core/main.ts"
  ],
  "evidenceRefs": [
    {
      "kind": "run",
      "ref": "81ecf2d7-e5de-4b7f-b7e3-c37e1bdbfc87",
      "sourceSystem": "aedis"
    },
    {
      "kind": "intent",
      "ref": "3a297041-63bd-42aa-9fc5-e8c9bd7ddec8",
      "sourceSystem": "aedis"
    }
  ],
  "relatedIds": [
    "aedis-outcome:81ecf2d7-e5de-4b7f-b7e3-c37e1bdbfc87",
    "aedis-run:81ecf2d7-e5de-4b7f-b7e3-c37e1bdbfc87",
    "aedis-task:81ecf2d7-e5de-4b7f-b7e3-c37e1bdbfc87"
  ],
  "relationships": [
    {
      "type": "run",
      "targetId": "aedis-run:81ecf2d7-e5de-4b7f-b7e3-c37e1bdbfc87"
    },
    {
      "type": "task",
      "targetId": "aedis-task:81ecf2d7-e5de-4b7f-b7e3-c37e1bdbfc87"
    }
  ],
  "metadata": {
    "suggestionCount": 2
  }
}
