{
  "id": "aedis-file:a23ebd01-a5e9-4256-a2d8-90b04e8d8549:src-h.ts",
  "space": "aedis/files",
  "kind": "aedis-file-touch",
  "title": "src/h.ts",
  "summary": "failed after modify in src/h.ts",
  "raw": "{\n  \"file\": \"src/h.ts\",\n  \"peers\": [],\n  \"scopeType\": \"cross-cutting-sweep\"\n}",
  "tags": [
    "ext:ts",
    "file-touch",
    "module:src",
    "verdict:failed"
  ],
  "createdAt": "2026-04-25T02:46:12.417Z",
  "updatedAt": "2026-04-25T02:46:12.420Z",
  "sourceSystem": "aedis",
  "repoId": "/mnt/ai/tmp/aedis-gauntlet-Ssa9m9",
  "filePaths": [
    "src/h.ts"
  ],
  "evidenceRefs": [
    {
      "kind": "run",
      "ref": "a23ebd01-a5e9-4256-a2d8-90b04e8d8549",
      "sourceSystem": "aedis"
    },
    {
      "kind": "intent",
      "ref": "221096fd-2668-4fd7-ab2c-c55086acecda",
      "sourceSystem": "aedis"
    }
  ],
  "relatedIds": [
    "aedis-outcome:a23ebd01-a5e9-4256-a2d8-90b04e8d8549",
    "aedis-run:a23ebd01-a5e9-4256-a2d8-90b04e8d8549",
    "aedis-task:a23ebd01-a5e9-4256-a2d8-90b04e8d8549"
  ],
  "relationships": [
    {
      "type": "run",
      "targetId": "aedis-run:a23ebd01-a5e9-4256-a2d8-90b04e8d8549"
    },
    {
      "type": "task",
      "targetId": "aedis-task:a23ebd01-a5e9-4256-a2d8-90b04e8d8549"
    }
  ],
  "metadata": {
    "scopeType": "cross-cutting-sweep",
    "clusterPeers": []
  }
}
