{
  "id": "aedis-suggestions:96b08683-ff2d-4a7f-b7d2-dd962c8ad56b",
  "space": "aedis/project/tmp-aedis-capreg-int-nmsupp",
  "kind": "aedis-suggestions",
  "title": "Follow-up suggestions for 96b08683-ff2d-4a7f-b7d2-dd962c8ad56b",
  "summary": "Re-run the task with tighter scope around the failing files before attempting broader changes. Address the merge blocker first: \"core/capability-registry.ts\" modified without original content or diff — cannot rollback",
  "tags": [
    "suggestions",
    "verdict:failed"
  ],
  "createdAt": "2026-04-19T22:42:44.911Z",
  "updatedAt": "2026-04-19T22:42:44.913Z",
  "sourceSystem": "aedis",
  "repoId": "/tmp/aedis-capreg-int-nMsUpP",
  "filePaths": [
    "core/capability-registry.ts"
  ],
  "evidenceRefs": [
    {
      "kind": "run",
      "ref": "96b08683-ff2d-4a7f-b7d2-dd962c8ad56b",
      "sourceSystem": "aedis"
    },
    {
      "kind": "intent",
      "ref": "f5ec9dda-b130-4848-ad4b-941409b45524",
      "sourceSystem": "aedis"
    }
  ],
  "relatedIds": [
    "aedis-outcome:96b08683-ff2d-4a7f-b7d2-dd962c8ad56b",
    "aedis-run:96b08683-ff2d-4a7f-b7d2-dd962c8ad56b",
    "aedis-task:96b08683-ff2d-4a7f-b7d2-dd962c8ad56b"
  ],
  "relationships": [
    {
      "type": "run",
      "targetId": "aedis-run:96b08683-ff2d-4a7f-b7d2-dd962c8ad56b"
    },
    {
      "type": "task",
      "targetId": "aedis-task:96b08683-ff2d-4a7f-b7d2-dd962c8ad56b"
    }
  ],
  "metadata": {
    "suggestionCount": 2
  }
}
