{
  "id": "aedis-outcome:57ce8898-0aa4-4a12-8efd-72288c46000c",
  "space": "aedis/failures",
  "kind": "aedis-failure",
  "title": "Failure in in core/capability-registry.ts, build capability registry",
  "summary": "\"core/capability-registry.ts\" modified without original content or diff — cannot rollback",
  "raw": "{\n  \"issues\": [],\n  \"mergeDecision\": {\n    \"action\": \"block\",\n    \"findings\": [\n      {\n        \"source\": \"integration-judge\",\n        \"severity\": \"critical\",\n        \"code\": \"judge:rollback-safety\",\n        \"message\": \"\\\"core/capability-registry.ts\\\" modified without original content or diff — cannot rollback\",\n        \"files\": [\n          \"core/capability-registry.ts\"\n        ]\n      },\n      {\n        \"source\": \"integration-judge\",\n        \"severity\": \"advisory\",\n        \"code\": \"judge:adversarial-guard\",\n        \"message\": \"builder changed 1 file(s) but scout read none — no corroboration for the changes\",\n        \"files\": [\n          \"core/capability-registry.ts\"\n        ]\n      },\n      {\n        \"source\": \"integration-judge\",\n        \"severity\": \"advisory\",\n        \"code\": \"judge:adversarial-guard\",\n        \"message\": \"intent-satisfaction score 0.60 (keywords: core, capability, registry, build)\",\n        \"files\": [\n          \"core/capability-registry.ts\"\n        ]\n      },\n      {\n        \"source\": \"change-set-gate\",\n        \"severity\": \"critical\",\n        \"code\": \"git-diff:expected-unchanged\",\n        \"message\": \"1 manifest file(s) expected to change but unchanged on disk: core/capability-registry.ts\",\n        \"files\": [\n          \"core/capability-registry.ts\"\n        ]\n      }\n    ],\n    \"critical\": [\n      {\n        \"source\": \"integration-judge\",\n        \"severity\": \"critical\",\n        \"code\": \"judge:rollback-safety\",\n        \"message\": \"\\\"core/capability-registry.ts\\\" modified without original content or diff — cannot rollback\",\n        \"files\": [\n          \"core/capability-registry.ts\"\n        ]\n      },\n      {\n        \"source\": \"change-set-gate\",\n        \"severity\": \"critical\",\n        \"code\": \"git-diff:expected-unchanged\",\n        \"message\": \"1 manifest file(s) expected to change but unchanged on disk: core/capability-registry.ts\",\n        \"files\": [\n          \"core/capability-registry.ts\"\n        ]\n      }\n    ],\n    \"advisory\": [\n      {\n        \"source\": \"integration-judge\",\n        \"severity\": \"advisory\",\n        \"code\": \"judge:adversarial-guard\",\n        \"message\": \"builder changed 1 file(s) but scout read none — no corroboration for the changes\",\n        \"files\": [\n          \"core/capability-registry.ts\"\n        ]\n      },\n      {\n        \"source\": \"integration-judge\",\n        \"severity\": \"advisory\",\n        \"code\": \"judge:adversarial-guard\",\n        \"message\": \"intent-satisfaction score 0.60 (keywords: core, capability, registry, build)\",\n        \"files\": [\n          \"core/capability-registry.ts\"\n        ]\n      }\n    ],\n    \"primaryBlockReason\": \"\\\"core/capability-registry.ts\\\" modified without original content or diff — cannot rollback\",\n    \"summary\": \"MERGE BLOCKED — 2 critical, 2 advisory\"\n  },\n  \"repairResult\": null\n}",
  "tags": [
    "ext:ts",
    "failure-pattern",
    "module:core",
    "verification:not-run"
  ],
  "createdAt": "2026-04-25T00:11:38.629Z",
  "updatedAt": "2026-04-25T00:11:38.631Z",
  "sourceSystem": "aedis",
  "repoId": "/tmp/aedis-capreg-int-e35QZC",
  "filePaths": [
    "core/capability-registry.ts"
  ],
  "evidenceRefs": [
    {
      "kind": "run",
      "ref": "57ce8898-0aa4-4a12-8efd-72288c46000c",
      "sourceSystem": "aedis"
    },
    {
      "kind": "intent",
      "ref": "40111c56-1fad-4d49-b362-24a946d851f8",
      "sourceSystem": "aedis"
    }
  ],
  "relatedIds": [
    "aedis-run:57ce8898-0aa4-4a12-8efd-72288c46000c",
    "aedis-task:57ce8898-0aa4-4a12-8efd-72288c46000c"
  ],
  "relationships": [
    {
      "type": "run",
      "targetId": "aedis-run:57ce8898-0aa4-4a12-8efd-72288c46000c"
    },
    {
      "type": "task",
      "targetId": "aedis-task:57ce8898-0aa4-4a12-8efd-72288c46000c"
    }
  ],
  "confidence": 0.35,
  "metadata": {
    "verdict": "failed",
    "verificationVerdict": "not-run",
    "primaryBlockReason": "\"core/capability-registry.ts\" modified without original content or diff — cannot rollback"
  }
}
