{
  "id": "aedis-outcome:e8a5d88e-137a-4edf-a3ff-e67752b2205e",
  "space": "aedis/failures",
  "kind": "aedis-failure",
  "title": "Failure in modify widget in core",
  "summary": "Files changed outside deliverables: core/widget.ts",
  "raw": "{\n  \"issues\": [],\n  \"mergeDecision\": {\n    \"action\": \"block\",\n    \"findings\": [\n      {\n        \"source\": \"integration-judge\",\n        \"severity\": \"critical\",\n        \"code\": \"judge:intent-alignment\",\n        \"message\": \"Files changed outside deliverables: core/widget.ts\",\n        \"files\": [\n          \"core/widget.ts\"\n        ]\n      },\n      {\n        \"source\": \"integration-judge\",\n        \"severity\": \"critical\",\n        \"code\": \"judge:rollback-safety\",\n        \"message\": \"\\\"core/widget.ts\\\" modified without original content or diff — cannot rollback\",\n        \"files\": [\n          \"core/widget.ts\"\n        ]\n      },\n      {\n        \"source\": \"integration-judge\",\n        \"severity\": \"critical\",\n        \"code\": \"judge:intent-alignment\",\n        \"message\": \"1 file(s) changed but not declared in manifest: core/widget.ts\",\n        \"files\": [\n          \"core/widget.ts\"\n        ]\n      },\n      {\n        \"source\": \"change-set-gate\",\n        \"severity\": \"critical\",\n        \"code\": \"git-diff:undeclared-changes\",\n        \"message\": \"1 file(s) changed on disk but not declared in manifest: core/widget.ts\",\n        \"files\": [\n          \"core/widget.ts\"\n        ]\n      }\n    ],\n    \"critical\": [\n      {\n        \"source\": \"integration-judge\",\n        \"severity\": \"critical\",\n        \"code\": \"judge:intent-alignment\",\n        \"message\": \"Files changed outside deliverables: core/widget.ts\",\n        \"files\": [\n          \"core/widget.ts\"\n        ]\n      },\n      {\n        \"source\": \"integration-judge\",\n        \"severity\": \"critical\",\n        \"code\": \"judge:rollback-safety\",\n        \"message\": \"\\\"core/widget.ts\\\" modified without original content or diff — cannot rollback\",\n        \"files\": [\n          \"core/widget.ts\"\n        ]\n      },\n      {\n        \"source\": \"integration-judge\",\n        \"severity\": \"critical\",\n        \"code\": \"judge:intent-alignment\",\n        \"message\": \"1 file(s) changed but not declared in manifest: core/widget.ts\",\n        \"files\": [\n          \"core/widget.ts\"\n        ]\n      },\n      {\n        \"source\": \"change-set-gate\",\n        \"severity\": \"critical\",\n        \"code\": \"git-diff:undeclared-changes\",\n        \"message\": \"1 file(s) changed on disk but not declared in manifest: core/widget.ts\",\n        \"files\": [\n          \"core/widget.ts\"\n        ]\n      }\n    ],\n    \"advisory\": [],\n    \"primaryBlockReason\": \"Files changed outside deliverables: core/widget.ts\",\n    \"summary\": \"MERGE BLOCKED — 4 critical, 0 advisory\"\n  },\n  \"repairResult\": null\n}",
  "tags": [
    "ext:ts",
    "failure-pattern",
    "module:core",
    "verification:not-run"
  ],
  "createdAt": "2026-04-21T14:36:52.691Z",
  "updatedAt": "2026-04-21T14:36:52.693Z",
  "sourceSystem": "aedis",
  "repoId": "/tmp/aedis-coord-int-UcCqbP",
  "filePaths": [
    "core/widget.ts"
  ],
  "evidenceRefs": [
    {
      "kind": "run",
      "ref": "e8a5d88e-137a-4edf-a3ff-e67752b2205e",
      "sourceSystem": "aedis"
    },
    {
      "kind": "intent",
      "ref": "32be9923-17df-4a91-86f4-d97138305aa7",
      "sourceSystem": "aedis"
    }
  ],
  "relatedIds": [
    "aedis-run:e8a5d88e-137a-4edf-a3ff-e67752b2205e",
    "aedis-task:e8a5d88e-137a-4edf-a3ff-e67752b2205e"
  ],
  "relationships": [
    {
      "type": "run",
      "targetId": "aedis-run:e8a5d88e-137a-4edf-a3ff-e67752b2205e"
    },
    {
      "type": "task",
      "targetId": "aedis-task:e8a5d88e-137a-4edf-a3ff-e67752b2205e"
    }
  ],
  "confidence": 0.35,
  "metadata": {
    "verdict": "failed",
    "verificationVerdict": "not-run",
    "primaryBlockReason": "Files changed outside deliverables: core/widget.ts"
  }
}
