{
  "id": "aedis-task:addb3ede-01e4-4541-bed7-b91c57b52433",
  "space": "aedis/project/mnt-ai-tmp-aedis-nest-bkezy6",
  "kind": "aedis-task",
  "title": "Add POST /users endpoint that calls MissingService.createUser with CreateUserDto in src/controllers.ts",
  "summary": "single-file · Retry failed: SentinelBuilder: must NOT be invoked when deterministic transform applies (original: Retry failed: SentinelBuilder: must NOT be invoked when deterministic transform applies (original: Worker threw: SentinelBuilder: must NOT be invoked when determinist…",
  "raw": "{\n  \"rawInput\": \"Add POST /users endpoint that calls MissingService.createUser with CreateUserDto in src/controllers.ts\",\n  \"normalizedPrompt\": \"Add POST /users endpoint that calls MissingService.createUser with CreateUserDto in src/controllers.ts\",\n  \"workerResults\": [\n    {\n      \"workerType\": \"scout\",\n      \"taskId\": \"9b5135a8-068f-414a-bee8-7f9000c5d0d3\",\n      \"success\": true,\n      \"output\": {\n        \"kind\": \"scout\",\n        \"dependencies\": [],\n        \"patterns\": [],\n        \"riskAssessment\": {\n          \"level\": \"low\",\n          \"factors\": [],\n          \"mitigations\": []\n        },\n        \"suggestedApproach\": \"ok\"\n      },\n      \"issues\": [],\n      \"cost\": {\n        \"model\": \"\",\n        \"inputTokens\": 0,\n        \"outputTokens\": 0,\n        \"estimatedCostUsd\": 0\n      },\n      \"confidence\": 0.9,\n      \"touchedFiles\": [],\n      \"assumptions\": [],\n      \"durationMs\": 1\n    },\n    {\n      \"workerType\": \"builder\",\n      \"taskId\": \"bf1f970e-030a-437e-ae47-e3d44aec70de\",\n      \"success\": false,\n      \"output\": {\n        \"kind\": \"scout\",\n        \"dependencies\": [],\n        \"patterns\": [],\n        \"riskAssessment\": {\n          \"level\": \"low\",\n          \"factors\": [],\n          \"mitigations\": []\n        },\n        \"suggestedApproach\": \"\"\n      },\n      \"issues\": [\n        {\n          \"severity\": \"error\",\n          \"message\": \"Retry failed: SentinelBuilder: must NOT be invoked when deterministic transform applies (original: Retry failed: SentinelBuilder: must NOT be invoked when deterministic transform applies (original: Worker threw: SentinelBuilder: must NOT be invoked when deterministic transform applies))\"\n        }\n      ],\n      \"cost\": {\n        \"model\": \"\",\n        \"inputTokens\": 0,\n        \"outputTokens\": 0,\n        \"estimatedCostUsd\": 0\n      },\n      \"confidence\": 0,\n      \"touchedFiles\": [],\n      \"assumptions\": [],\n      \"durationMs\": 0\n    },\n    {\n      \"workerType\": \"builder\",\n      \"taskId\": \"7845a1bc-55d2-4f4f-ae14-a719a95e2a5a\",\n      \"success\": false,\n      \"output\": {\n        \"kind\": \"scout\",\n        \"dependencies\": [],\n        \"patterns\": [],\n        \"riskAssessment\": {\n          \"level\": \"low\",\n          \"factors\": [],\n          \"mitigations\": []\n        },\n        \"suggestedApproach\": \"\"\n      },\n      \"issues\": [\n        {\n          \"severity\": \"error\",\n          \"message\": \"Worker threw: SentinelBuilder: must NOT be invoked when deterministic transform applies\"\n        }\n      ],\n      \"cost\": {\n        \"model\": \"\",\n        \"inputTokens\": 0,\n        \"outputTokens\": 0,\n        \"estimatedCostUsd\": 0\n      },\n      \"confidence\": 0,\n      \"touchedFiles\": [],\n      \"assumptions\": [],\n      \"durationMs\": 0\n    },\n    {\n      \"workerType\": \"builder\",\n      \"taskId\": \"ec3bb3a6-edd0-41b4-8760-0631055978b3\",\n      \"success\": false,\n      \"output\": {\n        \"kind\": \"scout\",\n        \"dependencies\": [],\n        \"patterns\": [],\n        \"riskAssessment\": {\n          \"level\": \"low\",\n          \"factors\": [],\n          \"mitigations\": []\n        },\n        \"suggestedApproach\": \"\"\n      },\n      \"issues\": [\n        {\n          \"severity\": \"error\",\n          \"message\": \"Worker threw: SentinelBuilder: must NOT be invoked when deterministic transform applies\"\n        }\n      ],\n      \"cost\": {\n        \"model\": \"\",\n        \"inputTokens\": 0,\n        \"outputTokens\": 0,\n        \"estimatedCostUsd\": 0\n      },\n      \"confidence\": 0,\n      \"touchedFiles\": [],\n      \"assumptions\": [],\n      \"durationMs\": 0\n    }\n  ]\n}",
  "tags": [
    "aedis-task",
    "scope:single-file",
    "verdict:failed"
  ],
  "createdAt": "2026-04-25T14:59:31.976Z",
  "updatedAt": "2026-04-25T14:59:31.977Z",
  "sourceSystem": "aedis",
  "repoId": "/mnt/ai/tmp/aedis-nest-bkEZy6",
  "evidenceRefs": [
    {
      "kind": "run",
      "ref": "addb3ede-01e4-4541-bed7-b91c57b52433",
      "sourceSystem": "aedis"
    },
    {
      "kind": "intent",
      "ref": "1bc2ee16-e7cd-4b98-b272-dbc6a248ddc1",
      "sourceSystem": "aedis"
    }
  ],
  "relatedIds": [
    "aedis-outcome:addb3ede-01e4-4541-bed7-b91c57b52433",
    "aedis-run:addb3ede-01e4-4541-bed7-b91c57b52433"
  ],
  "relationships": [
    {
      "type": "run",
      "targetId": "aedis-run:addb3ede-01e4-4541-bed7-b91c57b52433"
    },
    {
      "type": "outcome",
      "targetId": "aedis-outcome:addb3ede-01e4-4541-bed7-b91c57b52433"
    }
  ],
  "confidence": 0.35,
  "metadata": {
    "scopeType": "single-file",
    "complexityTier": "low",
    "verificationVerdict": "not-run",
    "filesTouched": 0
  }
}
