{
  "id": "aedis-file:baec4ef1-3dbb-454f-bb15-2ace5913061e:src-server.ts",
  "space": "aedis/files",
  "kind": "aedis-file-touch",
  "title": "src/server.ts",
  "summary": "partial after modify in src/server.ts",
  "raw": "{\n  \"file\": \"src/server.ts\",\n  \"peers\": [],\n  \"scopeType\": \"single-file\"\n}",
  "tags": [
    "ext:ts",
    "file-touch",
    "module:src",
    "verdict:partial"
  ],
  "createdAt": "2026-04-25T15:47:54.164Z",
  "updatedAt": "2026-04-25T15:47:54.168Z",
  "sourceSystem": "aedis",
  "repoId": "/mnt/ai/tmp/portum-lifecycle-oCpjyQ",
  "filePaths": [
    "src/server.ts"
  ],
  "evidenceRefs": [
    {
      "kind": "run",
      "ref": "baec4ef1-3dbb-454f-bb15-2ace5913061e",
      "sourceSystem": "aedis"
    },
    {
      "kind": "intent",
      "ref": "0c141ea3-5688-4b9a-8729-66460808bd0a",
      "sourceSystem": "aedis"
    },
    {
      "kind": "commit",
      "ref": "94f437e5d487c59136f681af192e18b1d68d0499",
      "sourceSystem": "aedis"
    },
    {
      "kind": "verification",
      "ref": "5b67a161-029b-443d-af12-0c40e2db51c3",
      "sourceSystem": "aedis"
    }
  ],
  "relatedIds": [
    "aedis-outcome:baec4ef1-3dbb-454f-bb15-2ace5913061e",
    "aedis-run:baec4ef1-3dbb-454f-bb15-2ace5913061e",
    "aedis-task:baec4ef1-3dbb-454f-bb15-2ace5913061e"
  ],
  "relationships": [
    {
      "type": "run",
      "targetId": "aedis-run:baec4ef1-3dbb-454f-bb15-2ace5913061e"
    },
    {
      "type": "task",
      "targetId": "aedis-task:baec4ef1-3dbb-454f-bb15-2ace5913061e"
    }
  ],
  "metadata": {
    "scopeType": "single-file",
    "clusterPeers": []
  }
}
