{
  "id": "aedis-task:644616ec-3088-4fd4-9cee-a3773007f438",
  "space": "aedis/project/tmp-aedis-capreg-int-icns1v",
  "kind": "aedis-task",
  "title": "in core/capability-registry.ts, build capability registry",
  "summary": "single-file · failed run · single-file scope · no files touched · verification not run",
  "raw": "{\n  \"rawInput\": \"in core/capability-registry.ts, build capability registry\",\n  \"normalizedPrompt\": \"in core/capability-registry.ts, build capability registry\",\n  \"workerResults\": [\n    {\n      \"workerType\": \"scout\",\n      \"taskId\": \"319bc80e-4334-4712-b97d-1841f3741cbb\",\n      \"success\": true,\n      \"output\": {\n        \"kind\": \"scout\",\n        \"dependencies\": [],\n        \"patterns\": [],\n        \"riskAssessment\": {\n          \"level\": \"low\",\n          \"factors\": [],\n          \"mitigations\": []\n        },\n        \"suggestedApproach\": \"no-op\"\n      },\n      \"issues\": [],\n      \"cost\": {\n        \"model\": \"\",\n        \"inputTokens\": 0,\n        \"outputTokens\": 0,\n        \"estimatedCostUsd\": 0\n      },\n      \"confidence\": 0.9,\n      \"touchedFiles\": [],\n      \"assumptions\": [],\n      \"durationMs\": 1\n    },\n    {\n      \"workerType\": \"builder\",\n      \"taskId\": \"3594a21e-6b16-48c1-8721-85c334c36176\",\n      \"success\": true,\n      \"output\": {\n        \"kind\": \"builder\",\n        \"changes\": [],\n        \"decisions\": [],\n        \"needsCriticReview\": false\n      },\n      \"issues\": [],\n      \"cost\": {\n        \"model\": \"\",\n        \"inputTokens\": 0,\n        \"outputTokens\": 0,\n        \"estimatedCostUsd\": 0\n      },\n      \"confidence\": 0.9,\n      \"touchedFiles\": [],\n      \"assumptions\": [],\n      \"durationMs\": 1\n    },\n    {\n      \"workerType\": \"critic\",\n      \"taskId\": \"3ef4de19-33e0-4afd-ada6-86a7ff2ae27c\",\n      \"success\": true,\n      \"output\": {\n        \"kind\": \"critic\",\n        \"verdict\": \"approve\",\n        \"comments\": [],\n        \"suggestedChanges\": [],\n        \"intentAlignment\": 0.9\n      },\n      \"issues\": [],\n      \"cost\": {\n        \"model\": \"\",\n        \"inputTokens\": 0,\n        \"outputTokens\": 0,\n        \"estimatedCostUsd\": 0\n      },\n      \"confidence\": 0.9,\n      \"touchedFiles\": [],\n      \"assumptions\": [],\n      \"durationMs\": 1\n    },\n    {\n      \"workerType\": \"verifier\",\n      \"taskId\": \"847bebce-4d3e-442f-932f-fa147319a0ac\",\n      \"success\": true,\n      \"output\": {\n        \"kind\": \"verifier\",\n        \"testResults\": [],\n        \"typeCheckPassed\": true,\n        \"lintPassed\": true,\n        \"buildPassed\": true,\n        \"passed\": true\n      },\n      \"issues\": [],\n      \"cost\": {\n        \"model\": \"\",\n        \"inputTokens\": 0,\n        \"outputTokens\": 0,\n        \"estimatedCostUsd\": 0\n      },\n      \"confidence\": 0.9,\n      \"touchedFiles\": [],\n      \"assumptions\": [],\n      \"durationMs\": 1\n    },\n    {\n      \"workerType\": \"integrator\",\n      \"taskId\": \"9e66bf99-77b2-4233-b98b-a68f2aa4bcf9\",\n      \"success\": true,\n      \"output\": {\n        \"kind\": \"integrator\",\n        \"finalChanges\": [],\n        \"conflictsResolved\": [],\n        \"coherenceCheck\": {\n          \"passed\": true,\n          \"checks\": []\n        },\n        \"readyToApply\": true\n      },\n      \"issues\": [],\n      \"cost\": {\n        \"model\": \"\",\n        \"inputTokens\": 0,\n        \"outputTokens\": 0,\n        \"estimatedCostUsd\": 0\n      },\n      \"confidence\": 0.9,\n      \"touchedFiles\": [],\n      \"assumptions\": [],\n      \"durationMs\": 1\n    }\n  ]\n}",
  "tags": [
    "aedis-task",
    "scope:single-file",
    "verdict:failed"
  ],
  "createdAt": "2026-04-24T23:15:44.418Z",
  "updatedAt": "2026-04-24T23:15:44.422Z",
  "sourceSystem": "aedis",
  "repoId": "/tmp/aedis-capreg-int-IcnS1V",
  "evidenceRefs": [
    {
      "kind": "run",
      "ref": "644616ec-3088-4fd4-9cee-a3773007f438",
      "sourceSystem": "aedis"
    },
    {
      "kind": "intent",
      "ref": "d1967de6-877d-4482-97dd-c1fce7cda2c4",
      "sourceSystem": "aedis"
    }
  ],
  "relatedIds": [
    "aedis-outcome:644616ec-3088-4fd4-9cee-a3773007f438",
    "aedis-run:644616ec-3088-4fd4-9cee-a3773007f438"
  ],
  "relationships": [
    {
      "type": "run",
      "targetId": "aedis-run:644616ec-3088-4fd4-9cee-a3773007f438"
    },
    {
      "type": "outcome",
      "targetId": "aedis-outcome:644616ec-3088-4fd4-9cee-a3773007f438"
    }
  ],
  "confidence": 0.35,
  "metadata": {
    "scopeType": "single-file",
    "complexityTier": "low",
    "verificationVerdict": "not-run",
    "filesTouched": 0
  }
}
