{
  "id": "aedis-suggestions:dfb50bf8-a768-4132-bdb2-96883386f0f7",
  "space": "aedis/project/mnt-ai-tmp-aedis-capreg-int-mm1pff",
  "kind": "aedis-suggestions",
  "title": "Follow-up suggestions for dfb50bf8-a768-4132-bdb2-96883386f0f7",
  "summary": "Re-run the task with tighter scope around the failing files before attempting broader changes. Address the merge blocker first: Missing deliverables: Modify core/capability-registry.ts",
  "tags": [
    "suggestions",
    "verdict:failed"
  ],
  "createdAt": "2026-04-25T13:49:24.796Z",
  "updatedAt": "2026-04-25T13:49:24.803Z",
  "sourceSystem": "aedis",
  "repoId": "/mnt/ai/tmp/aedis-capreg-int-Mm1pFf",
  "evidenceRefs": [
    {
      "kind": "run",
      "ref": "dfb50bf8-a768-4132-bdb2-96883386f0f7",
      "sourceSystem": "aedis"
    },
    {
      "kind": "intent",
      "ref": "43564440-9180-40c2-8eda-0a98dc96f5ad",
      "sourceSystem": "aedis"
    }
  ],
  "relatedIds": [
    "aedis-outcome:dfb50bf8-a768-4132-bdb2-96883386f0f7",
    "aedis-run:dfb50bf8-a768-4132-bdb2-96883386f0f7",
    "aedis-task:dfb50bf8-a768-4132-bdb2-96883386f0f7"
  ],
  "relationships": [
    {
      "type": "run",
      "targetId": "aedis-run:dfb50bf8-a768-4132-bdb2-96883386f0f7"
    },
    {
      "type": "task",
      "targetId": "aedis-task:dfb50bf8-a768-4132-bdb2-96883386f0f7"
    }
  ],
  "metadata": {
    "suggestionCount": 2
  }
}
