{
  "id": "aedis-file:2e1e2606-6052-4db3-ad57-08209e8b3664:readme.md",
  "space": "aedis/files",
  "kind": "aedis-file-touch",
  "title": "README.md",
  "summary": "failed after modify in README.md",
  "raw": "{\n  \"file\": \"README.md\",\n  \"peers\": [],\n  \"scopeType\": \"single-file\"\n}",
  "tags": [
    "ext:md",
    "file-touch",
    "module:README.md",
    "verdict:failed"
  ],
  "createdAt": "2026-04-21T23:48:35.659Z",
  "updatedAt": "2026-04-21T23:48:35.661Z",
  "sourceSystem": "aedis",
  "repoId": "/tmp/aedis-capreg-int-n7POEM",
  "filePaths": [
    "README.md"
  ],
  "evidenceRefs": [
    {
      "kind": "run",
      "ref": "2e1e2606-6052-4db3-ad57-08209e8b3664",
      "sourceSystem": "aedis"
    },
    {
      "kind": "intent",
      "ref": "5c6f21be-7863-440d-a29a-c0a61ccf28ab",
      "sourceSystem": "aedis"
    }
  ],
  "relatedIds": [
    "aedis-outcome:2e1e2606-6052-4db3-ad57-08209e8b3664",
    "aedis-run:2e1e2606-6052-4db3-ad57-08209e8b3664",
    "aedis-task:2e1e2606-6052-4db3-ad57-08209e8b3664"
  ],
  "relationships": [
    {
      "type": "run",
      "targetId": "aedis-run:2e1e2606-6052-4db3-ad57-08209e8b3664"
    },
    {
      "type": "task",
      "targetId": "aedis-task:2e1e2606-6052-4db3-ad57-08209e8b3664"
    }
  ],
  "metadata": {
    "scopeType": "single-file",
    "clusterPeers": []
  }
}
