{
  "id": "aedis-file:76f49fc7-56ed-4357-bb25-dcad77421944:src-server.ts",
  "space": "aedis/files",
  "kind": "aedis-file-touch",
  "title": "src/server.ts",
  "summary": "failed after modify in src/server.ts",
  "raw": "{\n  \"file\": \"src/server.ts\",\n  \"peers\": [],\n  \"scopeType\": \"single-file\"\n}",
  "tags": [
    "ext:ts",
    "file-touch",
    "module:src",
    "verdict:failed"
  ],
  "createdAt": "2026-04-25T13:49:24.850Z",
  "updatedAt": "2026-04-25T13:49:24.857Z",
  "sourceSystem": "aedis",
  "repoId": "/mnt/ai/tmp/aedis-portum-XDHp9t",
  "filePaths": [
    "src/server.ts"
  ],
  "evidenceRefs": [
    {
      "kind": "run",
      "ref": "76f49fc7-56ed-4357-bb25-dcad77421944",
      "sourceSystem": "aedis"
    },
    {
      "kind": "intent",
      "ref": "64dfa604-840b-42c9-9a95-8603eb15eeba",
      "sourceSystem": "aedis"
    },
    {
      "kind": "verification",
      "ref": "cd7ed268-fa1d-4781-9f8b-2c0aeef020fa",
      "sourceSystem": "aedis"
    }
  ],
  "relatedIds": [
    "aedis-outcome:76f49fc7-56ed-4357-bb25-dcad77421944",
    "aedis-run:76f49fc7-56ed-4357-bb25-dcad77421944",
    "aedis-task:76f49fc7-56ed-4357-bb25-dcad77421944"
  ],
  "relationships": [
    {
      "type": "run",
      "targetId": "aedis-run:76f49fc7-56ed-4357-bb25-dcad77421944"
    },
    {
      "type": "task",
      "targetId": "aedis-task:76f49fc7-56ed-4357-bb25-dcad77421944"
    }
  ],
  "metadata": {
    "scopeType": "single-file",
    "clusterPeers": []
  }
}
