{
  "id": "aedis-suggestions:45a4605a-3f0d-4fa8-8738-0e00fe1b7ca1",
  "space": "aedis/project/tmp-aedis-coord-int-mwxefd",
  "kind": "aedis-suggestions",
  "title": "Follow-up suggestions for 45a4605a-3f0d-4fa8-8738-0e00fe1b7ca1",
  "summary": "Re-run the task with tighter scope around the failing files before attempting broader changes. Address the merge blocker first: Missing deliverables: Modify widget.ts; Files changed outside deliverables: core/widget.ts",
  "tags": [
    "suggestions",
    "verdict:failed"
  ],
  "createdAt": "2026-04-21T23:38:10.224Z",
  "updatedAt": "2026-04-21T23:38:10.233Z",
  "sourceSystem": "aedis",
  "repoId": "/tmp/aedis-coord-int-MWxefD",
  "filePaths": [
    "core/widget.ts"
  ],
  "evidenceRefs": [
    {
      "kind": "run",
      "ref": "45a4605a-3f0d-4fa8-8738-0e00fe1b7ca1",
      "sourceSystem": "aedis"
    },
    {
      "kind": "intent",
      "ref": "76b69d27-a179-4a0e-acec-1029af64ad84",
      "sourceSystem": "aedis"
    }
  ],
  "relatedIds": [
    "aedis-outcome:45a4605a-3f0d-4fa8-8738-0e00fe1b7ca1",
    "aedis-run:45a4605a-3f0d-4fa8-8738-0e00fe1b7ca1",
    "aedis-task:45a4605a-3f0d-4fa8-8738-0e00fe1b7ca1"
  ],
  "relationships": [
    {
      "type": "run",
      "targetId": "aedis-run:45a4605a-3f0d-4fa8-8738-0e00fe1b7ca1"
    },
    {
      "type": "task",
      "targetId": "aedis-task:45a4605a-3f0d-4fa8-8738-0e00fe1b7ca1"
    }
  ],
  "metadata": {
    "suggestionCount": 2
  }
}
