{
  "id": "aedis-task:e8dcfd84-010a-4bf4-8bc4-93ada2b15c90",
  "space": "aedis/project/tmp-aedis-capreg-int-tmur06",
  "kind": "aedis-task",
  "title": "in core/capability-registry.ts, build capability registry",
  "summary": "single-file · failed run · single-file scope · no files touched · verification not run",
  "raw": "{\n  \"rawInput\": \"in core/capability-registry.ts, build capability registry\",\n  \"normalizedPrompt\": \"in core/capability-registry.ts, build capability registry\",\n  \"workerResults\": [\n    {\n      \"workerType\": \"scout\",\n      \"taskId\": \"4019804a-eab8-4d0b-a910-3afb84ccdc14\",\n      \"success\": true,\n      \"output\": {\n        \"kind\": \"scout\",\n        \"dependencies\": [],\n        \"patterns\": [],\n        \"riskAssessment\": {\n          \"level\": \"low\",\n          \"factors\": [],\n          \"mitigations\": []\n        },\n        \"suggestedApproach\": \"no-op\"\n      },\n      \"issues\": [],\n      \"cost\": {\n        \"model\": \"\",\n        \"inputTokens\": 0,\n        \"outputTokens\": 0,\n        \"estimatedCostUsd\": 0\n      },\n      \"confidence\": 0.9,\n      \"touchedFiles\": [],\n      \"assumptions\": [],\n      \"durationMs\": 1\n    },\n    {\n      \"workerType\": \"builder\",\n      \"taskId\": \"a0b8cfb6-4cc0-4a70-ade3-1a7b7d6a54fc\",\n      \"success\": true,\n      \"output\": {\n        \"kind\": \"builder\",\n        \"changes\": [],\n        \"decisions\": [],\n        \"needsCriticReview\": false\n      },\n      \"issues\": [],\n      \"cost\": {\n        \"model\": \"\",\n        \"inputTokens\": 0,\n        \"outputTokens\": 0,\n        \"estimatedCostUsd\": 0\n      },\n      \"confidence\": 0.9,\n      \"touchedFiles\": [],\n      \"assumptions\": [],\n      \"durationMs\": 1\n    },\n    {\n      \"workerType\": \"critic\",\n      \"taskId\": \"3baab5a7-014d-4cf5-8791-b9e55428bc58\",\n      \"success\": true,\n      \"output\": {\n        \"kind\": \"critic\",\n        \"verdict\": \"approve\",\n        \"comments\": [],\n        \"suggestedChanges\": [],\n        \"intentAlignment\": 0.9\n      },\n      \"issues\": [],\n      \"cost\": {\n        \"model\": \"\",\n        \"inputTokens\": 0,\n        \"outputTokens\": 0,\n        \"estimatedCostUsd\": 0\n      },\n      \"confidence\": 0.9,\n      \"touchedFiles\": [],\n      \"assumptions\": [],\n      \"durationMs\": 1\n    },\n    {\n      \"workerType\": \"verifier\",\n      \"taskId\": \"47b7cb02-d50d-4c1e-beae-2c5d736eb512\",\n      \"success\": true,\n      \"output\": {\n        \"kind\": \"verifier\",\n        \"testResults\": [],\n        \"typeCheckPassed\": true,\n        \"lintPassed\": true,\n        \"buildPassed\": true,\n        \"passed\": true\n      },\n      \"issues\": [],\n      \"cost\": {\n        \"model\": \"\",\n        \"inputTokens\": 0,\n        \"outputTokens\": 0,\n        \"estimatedCostUsd\": 0\n      },\n      \"confidence\": 0.9,\n      \"touchedFiles\": [],\n      \"assumptions\": [],\n      \"durationMs\": 1\n    },\n    {\n      \"workerType\": \"integrator\",\n      \"taskId\": \"d6a0fb70-0a5f-4979-aed9-e68fed58185d\",\n      \"success\": true,\n      \"output\": {\n        \"kind\": \"integrator\",\n        \"finalChanges\": [],\n        \"conflictsResolved\": [],\n        \"coherenceCheck\": {\n          \"passed\": true,\n          \"checks\": []\n        },\n        \"readyToApply\": true\n      },\n      \"issues\": [],\n      \"cost\": {\n        \"model\": \"\",\n        \"inputTokens\": 0,\n        \"outputTokens\": 0,\n        \"estimatedCostUsd\": 0\n      },\n      \"confidence\": 0.9,\n      \"touchedFiles\": [],\n      \"assumptions\": [],\n      \"durationMs\": 1\n    }\n  ]\n}",
  "tags": [
    "aedis-task",
    "scope:single-file",
    "verdict:failed"
  ],
  "createdAt": "2026-04-22T14:34:21.819Z",
  "updatedAt": "2026-04-22T14:34:21.823Z",
  "sourceSystem": "aedis",
  "repoId": "/tmp/aedis-capreg-int-tmuR06",
  "evidenceRefs": [
    {
      "kind": "run",
      "ref": "e8dcfd84-010a-4bf4-8bc4-93ada2b15c90",
      "sourceSystem": "aedis"
    },
    {
      "kind": "intent",
      "ref": "f096d85d-14b8-41d0-998d-79f1ef1c557d",
      "sourceSystem": "aedis"
    }
  ],
  "relatedIds": [
    "aedis-outcome:e8dcfd84-010a-4bf4-8bc4-93ada2b15c90",
    "aedis-run:e8dcfd84-010a-4bf4-8bc4-93ada2b15c90"
  ],
  "relationships": [
    {
      "type": "run",
      "targetId": "aedis-run:e8dcfd84-010a-4bf4-8bc4-93ada2b15c90"
    },
    {
      "type": "outcome",
      "targetId": "aedis-outcome:e8dcfd84-010a-4bf4-8bc4-93ada2b15c90"
    }
  ],
  "confidence": 0.35,
  "metadata": {
    "scopeType": "single-file",
    "complexityTier": "low",
    "verificationVerdict": "not-run",
    "filesTouched": 0
  }
}
