{
  "id": "aedis-suggestions:87d87f45-5cfa-4577-9cee-7806b64be54b",
  "space": "aedis/project/tmp-aedis-coord-int-ptvkuu",
  "kind": "aedis-suggestions",
  "title": "Follow-up suggestions for 87d87f45-5cfa-4577-9cee-7806b64be54b",
  "summary": "Re-run the task with tighter scope around the failing files before attempting broader changes. Address the merge blocker first: Files changed outside deliverables: core/widget.ts",
  "tags": [
    "suggestions",
    "verdict:failed"
  ],
  "createdAt": "2026-04-22T15:37:23.279Z",
  "updatedAt": "2026-04-22T15:37:23.280Z",
  "sourceSystem": "aedis",
  "repoId": "/tmp/aedis-coord-int-ptvkuu",
  "filePaths": [
    "core/widget.ts"
  ],
  "evidenceRefs": [
    {
      "kind": "run",
      "ref": "87d87f45-5cfa-4577-9cee-7806b64be54b",
      "sourceSystem": "aedis"
    },
    {
      "kind": "intent",
      "ref": "5cbd24d7-3836-4115-aeb9-55ce68477d72",
      "sourceSystem": "aedis"
    }
  ],
  "relatedIds": [
    "aedis-outcome:87d87f45-5cfa-4577-9cee-7806b64be54b",
    "aedis-run:87d87f45-5cfa-4577-9cee-7806b64be54b",
    "aedis-task:87d87f45-5cfa-4577-9cee-7806b64be54b"
  ],
  "relationships": [
    {
      "type": "run",
      "targetId": "aedis-run:87d87f45-5cfa-4577-9cee-7806b64be54b"
    },
    {
      "type": "task",
      "targetId": "aedis-task:87d87f45-5cfa-4577-9cee-7806b64be54b"
    }
  ],
  "metadata": {
    "suggestionCount": 2
  }
}
