{
  "id": "aedis-task:23d8419f-a9a3-4b56-b871-ee34a3bb586f",
  "space": "aedis/project/mnt-ai-tmp-aedis-gauntlet-lr8pwq",
  "kind": "aedis-task",
  "title": "modify core/util.ts to export 2",
  "summary": "single-file · failed run · single-file scope · 1 file(s) touched · verification not run",
  "raw": "{\n  \"rawInput\": \"modify core/util.ts to export 2\",\n  \"normalizedPrompt\": \"modify core/util.ts to export 2\",\n  \"workerResults\": [\n    {\n      \"workerType\": \"scout\",\n      \"taskId\": \"d0165fe0-53f0-413b-808c-1401c08c25cd\",\n      \"success\": true,\n      \"output\": {\n        \"kind\": \"scout\",\n        \"dependencies\": [],\n        \"patterns\": [],\n        \"riskAssessment\": {\n          \"level\": \"low\",\n          \"factors\": [],\n          \"mitigations\": []\n        },\n        \"suggestedApproach\": \"ok\"\n      },\n      \"issues\": [],\n      \"cost\": {\n        \"model\": \"\",\n        \"inputTokens\": 0,\n        \"outputTokens\": 0,\n        \"estimatedCostUsd\": 0\n      },\n      \"confidence\": 0.9,\n      \"touchedFiles\": [],\n      \"assumptions\": [],\n      \"durationMs\": 1\n    },\n    {\n      \"workerType\": \"builder\",\n      \"taskId\": \"8dfb0ac8-ac8a-44dc-bc5d-165c6879bfb9\",\n      \"success\": true,\n      \"output\": {\n        \"kind\": \"builder\",\n        \"changes\": [\n          {\n            \"path\": \"core/util.ts\",\n            \"operation\": \"modify\",\n            \"content\": \"export const x = 2;\\n\"\n          }\n        ],\n        \"decisions\": [],\n        \"needsCriticReview\": false\n      },\n      \"issues\": [],\n      \"cost\": {\n        \"model\": \"\",\n        \"inputTokens\": 0,\n        \"outputTokens\": 0,\n        \"estimatedCostUsd\": 0\n      },\n      \"confidence\": 0.9,\n      \"touchedFiles\": [\n        {\n          \"path\": \"core/util.ts\",\n          \"operation\": \"modify\"\n        }\n      ],\n      \"assumptions\": [],\n      \"durationMs\": 1\n    },\n    {\n      \"workerType\": \"critic\",\n      \"taskId\": \"55832ec5-35b0-413a-b514-fa1bed9eb2b5\",\n      \"success\": true,\n      \"output\": {\n        \"kind\": \"critic\",\n        \"verdict\": \"approve\",\n        \"comments\": [],\n        \"suggestedChanges\": [],\n        \"intentAlignment\": 0.9\n      },\n      \"issues\": [],\n      \"cost\": {\n        \"model\": \"\",\n        \"inputTokens\": 0,\n        \"outputTokens\": 0,\n        \"estimatedCostUsd\": 0\n      },\n      \"confidence\": 0.9,\n      \"touchedFiles\": [],\n      \"assumptions\": [],\n      \"durationMs\": 1\n    },\n    {\n      \"workerType\": \"verifier\",\n      \"taskId\": \"da5d2b84-dc5b-4290-918d-fa3a0950d1bc\",\n      \"success\": true,\n      \"output\": {\n        \"kind\": \"verifier\",\n        \"testResults\": [],\n        \"typeCheckPassed\": true,\n        \"lintPassed\": true,\n        \"buildPassed\": true,\n        \"passed\": true\n      },\n      \"issues\": [],\n      \"cost\": {\n        \"model\": \"\",\n        \"inputTokens\": 0,\n        \"outputTokens\": 0,\n        \"estimatedCostUsd\": 0\n      },\n      \"confidence\": 0.9,\n      \"touchedFiles\": [],\n      \"assumptions\": [],\n      \"durationMs\": 1\n    },\n    {\n      \"workerType\": \"integrator\",\n      \"taskId\": \"00634372-f7ec-4666-af08-85b3fbfc468c\",\n      \"success\": true,\n      \"output\": {\n        \"kind\": \"integrator\",\n        \"finalChanges\": [\n          {\n            \"path\": \"core/util.ts\",\n            \"operation\": \"modify\",\n            \"content\": \"export const x = 2;\\n\"\n          }\n        ],\n        \"conflictsResolved\": [],\n        \"coherenceCheck\": {\n          \"passed\": true,\n          \"checks\": []\n        },\n        \"readyToApply\": true\n      },\n      \"issues\": [],\n      \"cost\": {\n        \"model\": \"\",\n        \"inputTokens\": 0,\n        \"outputTokens\": 0,\n        \"estimatedCostUsd\": 0\n      },\n      \"confidence\": 0.9,\n      \"touchedFiles\": [\n        {\n          \"path\": \"core/util.ts\",\n          \"operation\": \"modify\"\n        }\n      ],\n      \"assumptions\": [],\n      \"durationMs\": 1\n    }\n  ]\n}",
  "tags": [
    "aedis-task",
    "change:modify",
    "ext:ts",
    "module:core",
    "scope:single-file",
    "verdict:failed"
  ],
  "createdAt": "2026-04-25T11:49:57.464Z",
  "updatedAt": "2026-04-25T11:49:57.466Z",
  "sourceSystem": "aedis",
  "repoId": "/mnt/ai/tmp/aedis-gauntlet-LR8Pwq",
  "filePaths": [
    "core/util.ts"
  ],
  "evidenceRefs": [
    {
      "kind": "run",
      "ref": "23d8419f-a9a3-4b56-b871-ee34a3bb586f",
      "sourceSystem": "aedis"
    },
    {
      "kind": "intent",
      "ref": "e79b472a-ec28-46ac-9756-b4193b346a4b",
      "sourceSystem": "aedis"
    }
  ],
  "relatedIds": [
    "aedis-outcome:23d8419f-a9a3-4b56-b871-ee34a3bb586f",
    "aedis-run:23d8419f-a9a3-4b56-b871-ee34a3bb586f"
  ],
  "relationships": [
    {
      "type": "run",
      "targetId": "aedis-run:23d8419f-a9a3-4b56-b871-ee34a3bb586f"
    },
    {
      "type": "outcome",
      "targetId": "aedis-outcome:23d8419f-a9a3-4b56-b871-ee34a3bb586f"
    }
  ],
  "confidence": 0.35,
  "metadata": {
    "scopeType": "single-file",
    "complexityTier": "low",
    "verificationVerdict": "not-run",
    "filesTouched": 1
  }
}
